{
    "$schema": "http://json-schema.org/draft-04/schema#",
    "Channels": {},
    "Event-Category": {
        "enum": [
            "nodes"
        ],
        "type": "string"
    },
    "Event-Name": {
        "enum": [
            "advertise"
        ],
        "type": "string"
    },
    "Expires": {},
    "Globals": {},
    "Media-Servers": {},
    "Node-Info": {},
    "Ports": {},
    "Processes": {},
    "Registrations": {},
    "Used-Memory": {},
    "Version": {},
    "WhApps": {},
    "Zone": {},
    "_id": "kapi.nodes.advertise",
    "description": "AMQP API for nodes.advertise",
    "md5": {},
    "properties": {},
    "required": [
        "Expires"
    ],
    "type": "object"
}
